{
  "Changes": [
    {
      "Action": "EditData",
      "Target": "furyx639.ToolbarIcons/Data",
      "Entries": {
        "furyx639.ToolbarIconsCP/ResetTerrainFeatures.Reset": {
          "ModId": "MabelSyrup.ResetTerrainFeatures",
          "Type": "Keybind",
          "ExtraData": "{{ResetTerrainFeaturesHotkey}}",
          "HoverText": "{{i18n: button.ResetTerrainFeatures}}"
        }
      }
    },
    {
      "Action": "EditData",
      "Target": "furyx639.FauxCore/Icons",
      "Entries": {
        "furyx639.ToolbarIconsCP/ResetTerrainFeatures.Reset": {
          "Area": { "X": 64, "Y": 16, "Width": 16, "Height": 16 },
          "Path": "{{InternalAssetKey: assets/icons.png}}"
        }
      }
    }
  ]
}